[
  {
    "id": "sdfsdaf33",
    "subject": "Hi there! How are you?",
    "senderName": "Mark",
    "senderEmail": "Mark2000@gmail.com",
    "body": "text from Mark text from Mark text from Mark text from Mark text from Mark text from Mark text from Mark "
  },
  {
    "id": "sd8fs25d32",
    "subject": "How are you?)",
    "senderName": "Hanna",
    "senderEmail": "HannaHey@gmail.com",
    "body": "text from everything and from Diana text from everything and from Diana text from everything and from Diana "
  },
  {
    "id": "23n23k2n2n5",
    "subject": "Hi booy! How are you?",
    "senderName": "Diana",
    "senderEmail": "Dianochka@gmail.com",
    "body": "hello im diana, i`m diana, Hello sadf  asdf asfaiojk njnre23"
  },
  {
    "id": "hh325jkh24h",
    "subject": "Man, what you doing?",
    "senderName": "Mum",
    "senderEmail": "MyMum@gmail.com",
    "body": "sdaf hh wmmg ! jkldsf? jadsfl3. sdaf hh wmmg ! jkldsf? jadsfl3. sdaf hh wmmg ! jkldsf? jadsfl3. sdaf hh wmmg ! jkldsf? jadsfl3."
  },
  {
    "id": "sd32edaf43",
    "subject": "Hi brother! How are you?",
    "senderName": "Max",
    "senderEmail": "MaxPower@gmail.com",
    "body": "text from Max text from Max text from Max text from Max text from Max text from Max text from Max "
  }

]